{
    "title": "216",
    "id": "216",
    "city": "Kutai Timur",
    "type": "Kabupaten",
    "province_id": "15",
    "province": "Kalimantan Timur",
    "number_of_districts" : "18",
    "data" : [{
        "id": "3043",
        "district": "Batu Ampar"
    }, {
        "id": "3044",
        "district": "Bengalon"
    }, {
        "id": "3045",
        "district": "Busang"
    }, {
        "id": "3046",
        "district": "Kaliorang"
    }, {
        "id": "3047",
        "district": "Karangan"
    }, {
        "id": "3048",
        "district": "Kaubun"
    }, {
        "id": "3049",
        "district": "Kongbeng"
    }, {
        "id": "3050",
        "district": "Long Mesangat (Mesengat)"
    }, {
        "id": "3051",
        "district": "Muara Ancalong"
    }, {
        "id": "3052",
        "district": "Muara Bengkal"
    }, {
        "id": "3053",
        "district": "Muara Wahau"
    }, {
        "id": "3054",
        "district": "Rantau Pulung"
    }, {
        "id": "3055",
        "district": "Sandaran"
    }, {
        "id": "3056",
        "district": "Sangatta Selatan"
    }, {
        "id": "3057",
        "district": "Sangatta Utara"
    }, {
        "id": "3058",
        "district": "Sangkulirang"
    }, {
        "id": "3059",
        "district": "Telen"
    }, {
        "id": "3060",
        "district": "Teluk Pandan"
    }]
}