{
    "title": "347",
    "id": "347",
    "city": "Pegunungan Bintang",
    "type": "Kabupaten",
    "province_id": "24",
    "province": "Papua",
    "number_of_districts" : "34",
    "data" : [{
        "id": "4857",
        "district": "Aboy"
    }, {
        "id": "4858",
        "district": "Alemsom"
    }, {
        "id": "4859",
        "district": "Awinbon"
    }, {
        "id": "4860",
        "district": "Batani"
    }, {
        "id": "4861",
        "district": "Batom"
    }, {
        "id": "4862",
        "district": "Bime"
    }, {
        "id": "4863",
        "district": "Borme"
    }, {
        "id": "4864",
        "district": "Eipumek"
    }, {
        "id": "4865",
        "district": "Iwur (Okiwur)"
    }, {
        "id": "4866",
        "district": "Jetfa"
    }, {
        "id": "4867",
        "district": "Kalomdol"
    }, {
        "id": "4868",
        "district": "Kawor"
    }, {
        "id": "4869",
        "district": "Kiwirok"
    }, {
        "id": "4870",
        "district": "Kiwirok Timur"
    }, {
        "id": "4871",
        "district": "Mofinop"
    }, {
        "id": "4872",
        "district": "Murkim"
    }, {
        "id": "4873",
        "district": "Nongme"
    }, {
        "id": "4874",
        "district": "Ok Aom"
    }, {
        "id": "4875",
        "district": "Okbab"
    }, {
        "id": "4876",
        "district": "Okbape"
    }, {
        "id": "4877",
        "district": "Okbemtau"
    }, {
        "id": "4878",
        "district": "Okbibab"
    }, {
        "id": "4879",
        "district": "Okhika"
    }, {
        "id": "4880",
        "district": "Oklip"
    }, {
        "id": "4881",
        "district": "Oksamol"
    }, {
        "id": "4882",
        "district": "Oksebang"
    }, {
        "id": "4883",
        "district": "Oksibil"
    }, {
        "id": "4884",
        "district": "Oksop"
    }, {
        "id": "4885",
        "district": "Pamek"
    }, {
        "id": "4886",
        "district": "Pepera"
    }, {
        "id": "4887",
        "district": "Serambakon"
    }, {
        "id": "4888",
        "district": "Tarup"
    }, {
        "id": "4889",
        "district": "Teiraplu"
    }, {
        "id": "4890",
        "district": "Weime"
    }]
}